electric/__init__.py
electric/_base_engine.py
electric/_feature_engine.py
electric/_model_engine.py
electric/electric_eel.py
electric_eel/__init__.py
electric_eel/_base_engine.py
electric_eel/_feature_engine.py
electric_eel/_model_engine.py
electric_eel/electric_eel.py
electriceel/__init__.py
electriceel/_base_engine.py
electriceel/_feature_engine.py
electriceel/_model_engine.py
electriceel/electric_eel.py
feature_platform/__init__.py
feature_platform/feature.py
metric_platform/__init__.py
metric_platform/metric.py
metric_platform/woe.py
model/__init__.py
model/classification.py
utils/__init__.py
utils/backtest.py
utils/exception.py
utils/log.py
utils/plot.py
utils/tools.py
electriceel-0.0.1.dist-info/METADATA
electriceel-0.0.1.dist-info/WHEEL
electriceel-0.0.1.dist-info/top_level.txt
electriceel-0.0.1.dist-info/RECORD
