Metadata-Version: 2.1
Name: electriceel
Version: 0.0.1
Summary: Model electriceel for model feature metric
Home-page: https://git.ty.ink/zhangpengfei/electric-eel
Author: zhangpengfei
Author-email: 1241833581@qq.com
License: UNKNOWN
Keywords: model-electriceel,scikit-learn,model,feature,metric
Platform: UNKNOWN
Requires-Python: >=3
Requires-Dist: lightgbm (==3.3.2)
Requires-Dist: numpy (==1.21.2)
Requires-Dist: pandas (==1.3.4)
Requires-Dist: Pillow (==8.4.0)
Requires-Dist: scikit-learn (==1.0.2)
Requires-Dist: tables (==3.6.1)
Requires-Dist: xgboost (==1.5.0)
